qtap/__init__.py
qtap/argument.py
qtap/function.py
qtap-0.1.2.dist-info/LICENSE
qtap-0.1.2.dist-info/METADATA
qtap-0.1.2.dist-info/WHEEL
qtap-0.1.2.dist-info/top_level.txt
qtap-0.1.2.dist-info/RECORD
