Metadata-Version: 2.1
Name: qtap
Version: 0.1.2
Summary: Automatic Qt parameter entry widgets using function signatures 
Home-page: https://github.com/kushalkolar/qtap
Author: Kushal Kolar
Author-email: kushalkolar@alumni.ubc.ca
License: GPL v3.0
Platform: UNKNOWN
Requires-Python: >=3.6
